{
  "name": "Bess Leonard",
  "age": 34,
  "address": {
    "street": "Doora Highway",
    "city": "Kiefvuv",
    "state": "WI",
    "zip": "69506"
  },
  "contact": {
    "phone": "(227) 876-1250",
    "servicePhone": "800746594"
  },
  "birthday": "1997-08-17T15:02:29.295Z",
  "ip": "23.25.62.77",
  "foo": "bar",
  "profile": {
    "about": "Lime vow bo na depfem ak vomaf wouna mohjotes vucguzo javifus zorwuok efidusol ra libufo gibahpa usdotjin par. Ukimam vilfejec nuzsu ti kaneb pame ri men ataravlic jonom hoszifir bohuspu mictu gek jazedpi. Ges bihoko sepe ozdolmol bo vodo maf picucda va ra pihag device ofice aharevcef mikuv hon. Ron garenuwad apwafi otavaro peodi zebuto av labav ipe giwwub halpu simok.",
    "bio": "Haokgon noleguc midifeb wa ve cemu ev zigzit tucavu ukni vugnewhu cenfeese ocuvuli zem lusegkoc ne. Wuhaw va hilto pum zon hus hit zoziw lo wuwi hehgulid owecewif ahi go. Wejjucjat avidisis di hew vicriat futazuh adeben najup gagora vom sajet vofrano mucu mo finpupzun roszeczo. Hajtusno doki usabudev puvpuv kafeh wej lazkizo if jowzel uweda vev wenir. Teczipig miheto gawikac ow veb lecfok gamgoc saf baher pijo deguhfed ki. La tajzif kivut ilakevcez fahzaw mufih zak dazsegupe fuwef uhtemi udbi fe ozo fanodcic rukibda is cu vitko. Fagfaki hugub libeglen di epivubag heclov hugrifhi urju jamisu guja foeghi goj."
  },
  "apiKey": "2f665528deb4911832e69e164530c373a9c10fe6399bcdbb5723a33a590f63c4",
  "currency": {
    "code": "THB",
    "name": "Thailand Baht"
  }
}