{
  "name": "Samuel Cohen",
  "age": 31,
  "address": {
    "street": "Fumi Ridge",
    "city": "Rabukufa",
    "state": "MN",
    "zip": "82039"
  },
  "contact": {
    "phone": "(329) 705-3382",
    "servicePhone": "800871956"
  },
  "birthday": "1972-12-01T06:34:50.313Z",
  "ip": "237.213.221.183",
  "foo": "bar",
  "profile": {
    "about": "Faje lenudla wogofo hivum sabegi tuel sevjo zimzaig puw odogotbe ationu os joofage gicgignu temoelu dogi ofoweso fo. Corrali ah ovfup we fijit upi nepcimoc rejas ne arigipnas jehobiaj ner pagogema. Len wub fooc nam jokfihab of sefiju ukorulit ige zuri bah putlodmo ahezar wow bu bumah. Ozetiswu ida sunewgol lighan jehuose vo uluigi wazpimod isgimbo lin colike lal cag epiricfu fa ibelaszil wefalawi.",
    "bio": "Udusumjup soofe nepirkaz jugcu nuijune wajujtub mucleb uc jod nuso vewug nibu kiftore be. Dusif ipudop cohgah ja men suguteb ziko mi be dan cu nifozvi kupa gievuj. Dutimaj gawhi cojib wucegon jereh poknowo bek onpicu jam ru ergiffu si alhuf tafunos fin wo jiubzaz hellina. Tami vece sawa jaapcec saropuj vubefzud enijha kafun bubejla ahaehuji edu vil ge rucno amhij. Jomda huave cufhu ibluwviz do zosvagafu nuzece amta zawmum ja wopba fuobafez nor kojnorju biv nabirago. Hiha riz usi puvtuka mogotid cis tiwew zeapoop sudopuj zovzitse ed imeizojif nipha ojnunhoc do keslehluf. Ukefovve va hahrodah ju tomonu jes coehazo gemdodugi afu givdot bu giljiluw ferno vun gu."
  },
  "apiKey": "0cb0777896fd3571068af9f19cc2f854864083c3376fb1db05380566c284ae06",
  "currency": {
    "code": "RSD",
    "name": "Serbia Dinar"
  }
}